ssupervisor/Supervisor.py
ssupervisor/__init__.py
ssupervisor/lib/__init__.py
ssupervisor/lib/config.py
ssupervisor/lib/logger.py
ssupervisor/lib/main.py
ssupervisor/lib/parser.py
ssupervisor/lib/process.py
ssupervisor/lib/watcher.py
ssupervisor-1.0.5.dist-info/entry_points.txt
ssupervisor-1.0.5.dist-info/WHEEL
ssupervisor-1.0.5.dist-info/METADATA
ssupervisor-1.0.5.dist-info/RECORD
